uvxtrigger/__init__.py
uvxtrigger/main.py
uvxtrigger-0.1.0.dist-info/METADATA
uvxtrigger-0.1.0.dist-info/WHEEL
uvxtrigger-0.1.0.dist-info/entry_points.txt
uvxtrigger-0.1.0.dist-info/RECORD
