Metadata-Version: 2.4
Name: uvxtrigger
Version: 0.1.0
Summary: A library that can execution command
Author-email: Your Name <your@email.com>
Classifier: License :: OSI Approved :: MIT License
Classifier: Operating System :: OS Independent
Classifier: Programming Language :: Python :: 3
Requires-Python: >=3.8
